pyuiw/__init__.py
pyuiw/__main__.py
pyuiw/uic/__init__.py
pyuiw/uic/Compiler/__init__.py
pyuiw/uic/Compiler/compiler.py
pyuiw/uic/Compiler/indenter.py
pyuiw/uic/Compiler/misc.py
pyuiw/uic/Compiler/proxy_type.py
pyuiw/uic/Compiler/qobjectcreator.py
pyuiw/uic/Compiler/qtproxies.py
pyuiw/uic/driver.py
pyuiw/uic/exceptions.py
pyuiw/uic/icon_cache.py
pyuiw/uic/objcreator.py
pyuiw/uic/port_v2/__init__.py
pyuiw/uic/port_v2/as_string.py
pyuiw/uic/port_v2/ascii_upper.py
pyuiw/uic/port_v2/invoke.py
pyuiw/uic/port_v2/load_plugin.py
pyuiw/uic/port_v2/proxy_base.py
pyuiw/uic/port_v2/string_io.py
pyuiw/uic/port_v3/__init__.py
pyuiw/uic/port_v3/as_string.py
pyuiw/uic/port_v3/ascii_upper.py
pyuiw/uic/port_v3/invoke.py
pyuiw/uic/port_v3/load_plugin.py
pyuiw/uic/port_v3/proxy_base.py
pyuiw/uic/port_v3/string_io.py
pyuiw/uic/properties.py
pyuiw/uic/uiparser.py
pyuiw/uic/widget-plugins/qtdeclarative.py
pyuiw/uic/widget-plugins/qtwebkit.py
pyuiw-0.2.4.dist-info/entry_points.txt
pyuiw-0.2.4.dist-info/LICENSE
pyuiw-0.2.4.dist-info/WHEEL
pyuiw-0.2.4.dist-info/METADATA
pyuiw-0.2.4.dist-info/RECORD
