Metadata-Version: 2.1
Name: pyuiw
Version: 0.2.4
Summary: Command Line File Watcher for Qt ui file to python file.
Home-page: https://github.com/FXTD-ODYSSEY/pyuiw
License: MIT
Author: timmyliang
Requires-Python: >=3.6.2,<3.10
Classifier: License :: OSI Approved :: MIT License
Classifier: Programming Language :: Python :: 3
Classifier: Programming Language :: Python :: 3.7
Classifier: Programming Language :: Python :: 3.8
Classifier: Programming Language :: Python :: 3.9
Requires-Dist: PySide2 (>=5.15.2,<6.0.0)
Requires-Dist: Qt.py (>=1.3.6,<2.0.0)
Requires-Dist: black (>=21.11b1,<22.0)
Requires-Dist: isort (>=5.10.1,<6.0.0)
Requires-Dist: toml (>=0.10.2,<0.11.0)
Project-URL: Repository, https://github.com/FXTD-ODYSSEY/pyuiw
